awards/__init__.py
awards/admin.py
awards/apps.py
awards/base.py
awards/config.py
awards/internals.py
awards/models.py
awards/notification.py
awards/pipeline.py
awards/serializers.py
awards/settings.py
awards/signals.py
awards/tasks.py
awards/urls.py
awards/views.py
awards/migrations/0001_initial.py
awards/migrations/__init__.py
awards/templatetags/__init__.py
awards/templatetags/badges_tags.py
django_awards-0.3.3.dist-info/DESCRIPTION.rst
django_awards-0.3.3.dist-info/METADATA
django_awards-0.3.3.dist-info/RECORD
django_awards-0.3.3.dist-info/WHEEL
django_awards-0.3.3.dist-info/metadata.json
django_awards-0.3.3.dist-info/top_level.txt
