Metadata-Version: 2.0
Name: django-awards
Version: 0.3.3
Summary: A Django Badge Awards application.
Home-page: https://github.com/fgmacedo/django-awards
Author: Fernando Macedo
Author-email: fgmacedo@gmail.com
License: MIT
Keywords: django-awards
Platform: UNKNOWN
Classifier: Development Status :: 3 - Alpha
Classifier: Framework :: Django
Classifier: Framework :: Django :: 1.8
Classifier: Framework :: Django :: 1.9
Classifier: Framework :: Django :: 1.10
Classifier: Intended Audience :: Developers
Classifier: License :: OSI Approved :: BSD License
Classifier: Natural Language :: English
Classifier: Programming Language :: Python :: 2
Classifier: Programming Language :: Python :: 2.7
Classifier: Programming Language :: Python :: 3
Classifier: Programming Language :: Python :: 3.4
Classifier: Programming Language :: Python :: 3.5
